jp_noui/__init__.py
jp_noui/_version.py
jp_noui/app.py
jp_noui/static/splash.html
jp_noui/static/style.css
jp_noui/static/test.html
jp_noui-0.3.7.data/data/share/jupyter/labextensions/jp-noui/package.json
jp_noui-0.3.7.data/data/share/jupyter/labextensions/jp-noui/static/568.67b27610af67101c9446.js
jp_noui-0.3.7.data/data/share/jupyter/labextensions/jp-noui/static/remoteEntry.906db554d44e88d2a3d4.js
jp_noui-0.3.7.data/data/share/jupyter/labextensions/jp-noui/static/style.js
jp_noui-0.3.7.data/data/share/jupyter/labextensions/jp-noui/static/third-party-licenses.json
jp_noui-0.3.7.data/data/share/jupyter/labextensions/jp-noui/install.json
jp_noui-0.3.7.dist-info/METADATA
jp_noui-0.3.7.dist-info/WHEEL
jp_noui-0.3.7.dist-info/entry_points.txt
jp_noui-0.3.7.dist-info/licenses/LICENSE
jp_noui-0.3.7.dist-info/RECORD
